flextream/__init__.py
flextream/_version.py
flextream/batch_handler.py
flextream/py.typed
flextream-0.1.2.dist-info/WHEEL
flextream-0.1.2.dist-info/METADATA
flextream-0.1.2.dist-info/RECORD
